mercy_reader/__init__.py
mercy_reader/mercury.py
mercy_reader/reader.py
mercy_reader-0.0.2.dist-info/LICENSE
mercy_reader-0.0.2.dist-info/METADATA
mercy_reader-0.0.2.dist-info/WHEEL
mercy_reader-0.0.2.dist-info/top_level.txt
mercy_reader-0.0.2.dist-info/RECORD
