Metadata-Version: 2.1
Name: mercy-reader
Version: 0.0.2
Summary: Convert web page into other formats.
Home-page: https://github.com/hex0cter/mercy-reader
Author: Daniel Han
Author-email: hex0cter@gmail.com
Maintainer: Daniel Han
Maintainer-email: hex0cter@gmail.com
License: MIT
Platform: UNKNOWN
Classifier: Development Status :: 4 - Beta
Classifier: Framework :: Pytest
Classifier: Intended Audience :: Developers
Classifier: Topic :: Software Development :: Quality Assurance
Classifier: Topic :: Software Development :: Testing
Classifier: Topic :: Utilities
Classifier: Programming Language :: Python :: 3.7
Classifier: Programming Language :: Python :: 3.8
Classifier: Programming Language :: Python :: Implementation :: CPython
Classifier: Programming Language :: Python :: Implementation :: PyPy
Classifier: Operating System :: OS Independent
Classifier: License :: OSI Approved :: MIT License
Requires-Python: >=3.6, !=3.0.*, !=3.1.*, !=3.2.*, !=3.3.*
Requires-Dist: certifi (==2018.11.29)
Requires-Dist: chardet (==3.0.4)
Requires-Dist: html2text (==2018.1.9)
Requires-Dist: idna (==2.8)
Requires-Dist: Naked (==0.1.31)
Requires-Dist: PyYAML (==5.4)
Requires-Dist: requests (==2.25.1)
Requires-Dist: urllib3 (==1.26.4)
